kola/__init__.py
kola/__main__.py
kola/_cutil.h
kola/_cutil.pxd
kola/_yylex.pxd
kola/exception.py
kola/lexer.cpython-313t-x86_64-linux-gnu.so
kola/lexer.pxd
kola/lexer.pyi
kola/parser.cpython-313t-x86_64-linux-gnu.so
kola/parser.pxd
kola/parser.pyi
kola/version.py
kola/writer.cpython-313t-x86_64-linux-gnu.so
kola/writer.pxd
kola/writer.pyi
kola/klvm/__init__.py
kola/klvm/command.py
kola/klvm/commandset.py
kola/klvm/commandset.pyi
kola/klvm/decorator.py
kola/klvm/decorator.pyi
kola/klvm/environment.py
kola/klvm/handler.py
kola/klvm/koilang.py
kola/klvm/mask.py
kola/klvm/writer.py
kola/lib/__init__.py
kola/lib/fastfiles.py
kola/lib/recorder.py
kola/lib/debugger/__init__.py
kola/lib/debugger/base.py
kola/lib/debugger/command_debugger.py
kola/lib/debugger/default_runner.py
koilang-1.1.2.dist-info/METADATA
koilang-1.1.2.dist-info/WHEEL
koilang-1.1.2.dist-info/top_level.txt
koilang-1.1.2.dist-info/RECORD
koilang-1.1.2.dist-info/licenses/LICENSE
