Metadata-Version: 2.1
Name: KoiLang
Version: 1.1.2
Summary: simple python module for KoiLang parsing
Home-page: https://github.com/Ovizro/Kola
Author: Visecy
Author-email: Visecy@visecy.top
Maintainer: Ovizro
Maintainer-email: Ovizro@visecy.top
License: Apache 2.0
Classifier: Development Status :: 5 - Production/Stable
Classifier: License :: OSI Approved :: Apache Software License
Classifier: Programming Language :: C
Classifier: Programming Language :: Cython
Classifier: Programming Language :: Python :: 3
Classifier: Programming Language :: Python :: 3 :: Only
Classifier: Programming Language :: Python :: 3.6
Classifier: Programming Language :: Python :: 3.7
Classifier: Programming Language :: Python :: 3.8
Classifier: Programming Language :: Python :: 3.9
Classifier: Programming Language :: Python :: 3.10
Classifier: Topic :: Software Development :: Libraries :: Python Modules
Classifier: Topic :: Text Processing :: Markup
Requires-Python: >=3.6
License-File: LICENSE
Requires-Dist: typing-extensions <4.14,>=4.0
